{
  "@context": [
    "https://www.w3.org/2018/credentials/v1",
    "https://vc-context.elia.be/2022/v1/device-info"
  ],
  "type": [
    "VerifiableCredential",
    "DeviceInfoCredential"
  ],
  "id": "<some URI, e.g. https://elia.be/credential/1>",
  "credentialSubject": {
    "type": "Device",
    "id": "deviceIdScheme:123",
    "brandName": "Device Manufacturer Inc",
    "deviceCode": "device 123",
    "deviceName": "Washing Machine 3000",
    "manufacturerDescription": "A next-gen washing machine",
    "manufacturerLabel": "WM-3000",
    "hardwareRevision": "revision1"
  },
  "issuer": "did:example:dso",
  "issuanceDate": "2021-05-14T12:55:30Z",
  "render": {
    "type": "DIFWalletRenderingHint",
    "id": "https://vc-context.elia.be/2022/v1/device-info/data-display"
  }
}